MANIFEST.in
README.md
setup.py
jobtastic_mixins.egg-info/PKG-INFO
jobtastic_mixins.egg-info/SOURCES.txt
jobtastic_mixins.egg-info/dependency_links.txt
jobtastic_mixins.egg-info/requires.txt
jobtastic_mixins.egg-info/top_level.txt
jobtastic_mixins.egg-info/zip-safe
jobtasticmixins/__init__.py
jobtasticmixins/mixins.py