Metadata-Version: 1.1
Name: jobtastic-mixins
Version: 0.1
Summary: Provides ability calculate average time of tasks
Home-page: https://github.com/abbasovalex/JobtasticMixins
Author: Abbasov Alexander
Author-email: abbasovalex@{nospam}gmail.com
License: MIT
Platform: any
Classifier: Development Status :: 3 - Alpha
Classifier: Intended Audience :: Developers
Classifier: License :: OSI Approved :: MIT License
Classifier: Operating System :: OS Independent
Classifier: Programming Language :: Python
Classifier: Programming Language :: Python :: 2.6
Classifier: Programming Language :: Python :: 2.7
Classifier: Topic :: Internet :: WWW/HTTP
